{
  "title": "Natural Language Processing (NLP) and Tokenization",
  "content": [
    {
      "text": "Natural Language Processing (NLP) is a field of artificial intelligence that focuses on the interaction between computers and humans through natural language.",
      "keywords": [
        {
          "term": "Natural Language Processing",
          "hint": "A subfield of AI that enables machines to understand and process human language."
        },
        {
          "term": "artificial intelligence",
          "hint": "The simulation of human intelligence in machines."
        }
      ]
    },
    {
      "text": "Tokenization is a fundamental step in NLP where text is split into smaller units called tokens, such as words or sentences.",
      "keywords": [
        {
          "term": "Tokenization",
          "hint": "The process of breaking down text into smaller units like words, phrases, or symbols."
        },
        {
          "term": "tokens",
          "hint": "Individual units of text, such as words or sentences, produced by tokenization."
        }
      ]
    }
  ],
  "settings": {
    "fontOptions": ["Arial", "Times New Roman", "Courier New", "Verdana"],
    "defaultFont": "Arial",
    "textSizeOptions": ["Small", "Medium", "Large"],
    "defaultTextSize": "Medium",
    "themeOptions": ["Light", "Dark"],
    "defaultTheme": "Light"
  }
}